LICENSE.txt
MANIFEST.in
README.md
VERSION
requirements.txt
setup.py
pyncml/__init__.py
pyncml/pyncml.py
pyncml/test_pyncml.py
pyncml.egg-info/PKG-INFO
pyncml.egg-info/SOURCES.txt
pyncml.egg-info/dependency_links.txt
pyncml.egg-info/requires.txt
pyncml.egg-info/top_level.txt