Metadata-Version: 1.1
Name: pyncml
Version: 0.0.9
Summary: A simple python library to apply NcML logic to NetCDF files
Home-page: https://github.com/axiom-data-science/pyncml
Author: Kyle Wilcox
Author-email: kyle@axiomdatascience.com
License: MIT
Platform: UNKNOWN
Classifier: Development Status :: 3 - Alpha
Classifier: Intended Audience :: Developers
Classifier: Intended Audience :: Science/Research
Classifier: License :: OSI Approved :: MIT License
Classifier: Operating System :: POSIX :: Linux
Classifier: Programming Language :: Python
Classifier: Topic :: Scientific/Engineering
